Animefetch/__init__.py
Animefetch/script.py
Animefetch-0.0.3.dist-info/METADATA
Animefetch-0.0.3.dist-info/WHEEL
Animefetch-0.0.3.dist-info/top_level.txt
Animefetch-0.0.3.dist-info/RECORD
