Metadata-Version: 2.1
Name: Animefetch
Version: 0.0.3
Summary: Anime Command-Line System Information Tool
Home-page: https://github.com/Thadeuks
Author: Tadeo Asael 'Thadeuks'
Author-email: ass.hurtado2008@gmail.com
License: MIT
Platform: UNKNOWN
Requires-Dist: colorama
Requires-Dist: psutil
